qpth/__init__.py
qpth/qp.py
qpth/util.py
qpth/solvers/__init__.py
qpth/solvers/cvxpy.py
qpth/solvers/np.py
qpth/solvers/pdipm/__init__.py
qpth/solvers/pdipm/batch.py
qpth/solvers/pdipm/single.py
qpth-0.0.2.dist-info/DESCRIPTION.rst
qpth-0.0.2.dist-info/METADATA
qpth-0.0.2.dist-info/RECORD
qpth-0.0.2.dist-info/WHEEL
qpth-0.0.2.dist-info/metadata.json
qpth-0.0.2.dist-info/top_level.txt
