Metadata-Version: 2.0
Name: qpth
Version: 0.0.2
Summary: A fast and differentiable QP solver for PyTorch.
Home-page: https://github.com/locuslab/qpth
Author: Brandon Amos
Author-email: bamos@cs.cmu.edu
License: Apache 2.0
Platform: any
Requires-Dist: numpy (>=1<2)
